repod/__init__.py
repod/cli.py
repod/core.py
repod/py.typed
repod_cli-0.0.4.dist-info/METADATA
repod_cli-0.0.4.dist-info/WHEEL
repod_cli-0.0.4.dist-info/entry_points.txt
repod_cli-0.0.4.dist-info/licenses/LICENSE
repod_cli-0.0.4.dist-info/RECORD
