Metadata-Version: 2.4
Name: repod-cli
Version: 0.0.4
Summary: REPOsitory Dumper
Author-email: "Shoji, Yutaka" <ytk.shoji@gmail.com>
License-File: LICENSE
Requires-Python: >=3.10
Requires-Dist: click>=8.1.8
Requires-Dist: rich>=13.9.4
Requires-Dist: treelib>=1.7.0
